CHANGELOG.txt
LICENSE.txt
MANIFEST.in
README.txt
setup.py
FinScience/__init__.py
FinScience.egg-info/PKG-INFO
FinScience.egg-info/SOURCES.txt
FinScience.egg-info/dependency_links.txt
FinScience.egg-info/top_level.txt
FinScience/SiSS/SiSS.py
FinScience/SiSS/__init__.py
FinScience/SiSS/check_col.py
FinScience/SiSS/get_slope.py
FinScience/TI-SiSS/TI-SiSS.py
FinScience/TI-SiSS/__init__.py
FinScience/TI-SiSS/check_col.py
FinScience/TI-SiSS/get_slope.py
FinScience/TrendIndicator/Trend_Indicator.py
FinScience/TrendIndicator/__init__.py
FinScience/TrendIndicator/check_col.py
FinScience/TrendIndicator_for_MultIndex/Trend_Indicator_for_MultIndex.py
FinScience/TrendIndicator_for_MultIndex/__init__.py
FinScience/TrendIndicator_for_MultIndex/check_col.py