Metadata-Version: 2.1
Name: FinScience
Version: 0.6
Summary: A trend indicator and two algoritmic trading strategies based on the alternative data provided by FinScience
Home-page: UNKNOWN
Author: Andrea Frattini
Author-email: andreafrattini20@gmail.com
License: MIT
Keywords: finscience
Platform: UNKNOWN
Classifier: Development Status :: 4 - Beta
Classifier: Environment :: MacOS X
Classifier: Framework :: Jupyter
Classifier: Intended Audience :: Science/Research
Classifier: Operating System :: MacOS
Classifier: License :: OSI Approved :: MIT License
Classifier: Programming Language :: Python :: 3.10
License-File: LICENSE.txt
